[
  {
    "id": "rule_1",
    "rule": "The output must be presented as a bullet-pointed or numbered list.",
    "inverseRule": "The output must not be presented using any sequential marker.",
    "inversed": false
  },
  {
    "id": "rule_2",
    "rule": "Each item in the list represents an extracted entity from the input text.",
    "inverseRule": "Each item in the list does not represent an extracted entity from the input text.",
    "inversed": false
  },
  {
    "id": "rule_3",
    "rule": "Each entity is preceded by its type of classification: company name, people name, specific topic, or general theme.",
    "inverseRule": "Each entity's type of classification does not follow a fixed pattern.",
    "inversed": false
  },
  {
    "id": "rule_4",
    "rule": "It should be clear and unambiguous how each section is organized and what distinguishes one category of entities from another.",
    "inverseRule": "It should be intentionally ambiguous how each section is organized to test understanding.",
    "inversed": false
  },
  {
    "id": "rule_5",
    "rule": "The input text will determine which of these categories apply to a given word or phrase in the output list.",
    "inverseRule": "The input text will not relate to any category in the output list.",
    "inversed": false
  }
]