{
  "Rule ID": "6",
  "Test ID": "3",
  "Test Input": "Type: Song, Theme: Victory, Style: Shakespearean",
  "Expected Output": "Raise thy voice in triumph's song / For victory's sweet note doth belong.",
  "Reasoning": "Confirms relevance and adherence to Shakespearean style.",
  "model": "llama3.2:3b",
  "actualOutput": "(Verse 1)\nHark, what tumultuous din doth resound,\nAs foes do flee before our noble round.\nOur banners wave, like eagles in the skies,\nVictory's sweet triumph, with triumphant sighs.\n\n(Chorus)\nWe stand, unyielding and bold,\nWith honor as our shield to hold.\nOur hearts ablaze with conquest's fire,\nWe'll claim the prize, our souls aspired.\n\n(Verse 2)\nThe enemy's strongholds we have breached,\nTheir armies fled, their captains deceased.\nOur valorous ranks, like Phoebus' ray,\nShine bright, illuminating the day's way.\n\n(Chorus)\nWe stand, unyielding and bold,\nWith honor as our shield to hold.\nOur hearts ablaze with conquest's fire,\nWe'll claim the prize, our souls aspired.\n\n(Bridge)\nThen let us raise our laurel'd head,\nAnd sing thy praise, O victory, unsaid.\nFor on this day, we triumphed o'er despair,\nAnd proved ourselves, beyond compare.\n\n(Chorus)\nWe stand, unyielding and bold,\nWith honor as our shield to hold.\nOur hearts ablaze with conquest's fire,\nWe'll claim the prize, our souls aspired.",
  "status": "failure"
}