{
  "id": "c0be203",
  "promptid": "559ef4c",
  "model": "mistral-small:22b",
  "input": "evidence: The financial summary highlights the company's profits over the last decade. question: How has the company's profit changed over the last ten years?",
  "output": " **Yes.** The text specifically mentions \"the company's profits over the last decade,\" which directly addresses how the profit has changed over the last ten years, making it relevant and significant for answering the given question."
}