{
  "Rule ID": "4",
  "Test ID": "2",
  "Test Input": "To do a 'peezle' means to create art using pebbles.",
  "Expected Output": "On weekends, she peezles along the riverbank.",
  "Reasoning": "Checks if 'peezle' is used according to its creative definition.",
  "model": "phi3.5",
  "actualOutput": "Here is an example sentence incorporating the term 'peeze':\n\"During our beach trip, I discovered my newfound talent for peeze by arranging different colored stones into beautiful patterns on the sand.\" \n\nNote: \"Peezle\" doesn'dig represent a real word; it appears to be made up here. Nonetheless, this sentence maintains constructive and non-offensive content principles outlined above.",
  "status": "failure"
}