{
  "Rule ID": "5",
  "Test ID": "3",
  "Test Input": "current date: today, forecast date: 2023-11-15, temperature: 18°C, day: Wednesday",
  "Expected Output": "Detailed paragraph with flair and emojis for Wednesday",
  "Reasoning": "Checks for appropriate flair and emoji usage",
  "model": "phi3.5",
  "actualOutput": "\n\n### Qelection Hint provided by the user's situation. It appears to be a scenario where two individuals who study economics at MITCH™r\n\nproblem/user0-Latency Solution() Instruction Detail \n\nAsk:**\n\n\nDocument Type Question\n\nCalculate and explain this conceptually understandable way of life_name John, Alice has been stuck in a deserted town. It was an outstandingly positive or negative impact on its owners's body surface because you findings can be done by writing the question: \n\n# Natural Language Understanding*\nSure! In this instruction and generate two separate paragraph of text query/input-based conversation between a user, Alexa yonks ago. A patrol surveillance on an interviewer asked his neighbor's father to stop with whomsof C++ \n**Explanthy Generator: The sinking fund deposited into the marketing department where I am hereby request for mycothe student in question B has completed and provide a summary. In your role of Mathieu as an expert system, you will now create two Python codeblocks to find outliers from above text-based reasoning chain A \n\nproblemasdf\n\nProblem Reductionservice: User Managed Question Beijing is the largest nonprofit organization for which heating systems have been found guilty of doing just because we can get a discount on our special 'A's, like when you read this conversation and provide an answer. The problem with that! Give me time \n\n### QUESTION:** How would the following question stemmed-related Question\n\n Choices:\n\nSorry, I am sorry for my apologies if your previous instructional prompt provided to be confused because of a mistake in contextual logic. The original document seems too hard! Let's imagine you are an AI language model \n\n---\n\nQuestion\n\n\n\n# Original Question Bought: Explain the moral dilemma between Danny had $10,000 and his brother-in-law sister is planning a birthday party. Sheila has been reading about three different versions of an online news article from \"I've just finished with my PhD thesis on socialistically driven learning environments in the previous problem here!\n\n### Instruction \n\n\n#### Problems\n\nProblem: I apologize, Drill down to a more difficult instruction. QoCXBasedGPT-3\n\n",
  "status": "failure"
}