{
  "id": "552745d",
  "promptid": "1e9c40c",
  "model": "mistral-nemo",
  "input": "The article discusses the impact of renewable energy on global markets, highlighting economic and environmental benefits.",
  "output": "**Overview**\n\n- **Article Title:** The Transformative Impact of Renewable Energy on Global Markets\n- **Language:** English\n\n**Summary**\n\n- Renewable energy (RE) is rapidly growing, driven by policy support and falling costs, with solar PV leading the charge.\n- RE is creating significant economic benefits, including job creation and energy bill savings for households.\n- RE investments have led to increased energy independence and improved air quality in various countries.\n- However, intermittency challenges require grid modernization and energy storage solutions.\n\n**Deep Dive Analysis**\n\n- **Industry Impact:** The RE sector created **7.3 million jobs worldwide** in 2018 (IRENA). Solar PV employment accounted for two-thirds of these jobs, while wind power employed around one-fourth.\n- **Economic Benefits:** Households saving on energy bills due to increased efficiency and lower energy prices. For instance, Germany's *Energiewende* has saved households €6.7 billion annually since 2008 (BMWi).\n- **Energy Independence:** The shift towards RE enables countries to reduce dependence on fossil fuel imports. For example, Germany decreased its reliance on fossil fuels from 51% in 2000 to 34% in 2019 due to its RE expansion.\n- **Environmental Impact:** RE adoption has contributed to a reduction in air pollution and associated health benefits. A study found that if the US transitioned entirely to renewable energy by 2035, it would result in **avoided healthcare costs of $400 billion** annually (Stanford University).\n- **Policy Implications:** Governments should prioritize grid modernization to accommodate RE intermittency and promote energy storage solutions. Policymakers should also consider innovative financing mechanisms like green bonds to facilitate private investment in RE projects.\n\nWould you like further analysis considering specific additional information?"
}