{
  "id": "631c017",
  "promptid": "1e9c40c",
  "model": "mistral-small:22b",
  "input": "El presidente anunció nuevas medidas económicas para mejorar la situación del país. Estas incluyen la reducción de impuestos y el aumento del gasto en infraestructura.",
  "output": " ## Overview\n\n## Summary\n\n### Key Points:\n- **Economic Measures Announced:** The President has announced new economic measures aimed at improving the country's situation.\n- **Tax Reduction:** This includes a reduction in taxes.\n- **Infrastructure Investment:** Additionally, there is an increase in spending on infrastructure.\n\n### One-Paragraph Summary:\nThe President recently announced new economic initiatives to enhance the country’s overall situation. These measures include reducing tax rates and increasing investment in infrastructure projects.\n\n## Deep Dive Analysis\n\n### Economic Impact:\n- **Tax Reduction:** A reduction in taxes can stimulate consumer spending by increasing disposable income. This could lead to a short-term economic boost.\n- **Infrastructure Spending:** Increased investment in infrastructure can have long-term benefits such as improved public services, job creation, and enhanced economic growth through better connectivity and efficiency.\n\n### Political Economy:\n- **Public Reception:** These measures may be well-received by the general public who are looking for immediate financial relief and long-term development.\n- **Government Spending:** The balance between reducing taxes and increasing spending will need to be carefully managed to avoid fiscal deficits.\n\n### Industry Implications:\n- **Construction Sector:** Infrastructure projects can provide a significant boost to the construction sector, creating jobs and stimulating associated industries like materials supply.\n- **Business Environment:** The combined effect of tax reduction and infrastructure development may attract foreign investment by making the business environment more attractive.\n\n### Social Impact:\n- **Employment Opportunities:** Increased infrastructure spending can lead to job creation in various skill levels, benefiting local communities.\n- **Public Services:** Improved infrastructure can enhance public services like transportation, communication, and healthcare, leading to a better quality of life for citizens.\n\n### Potential Challenges:\n- **Implementation:** Efficient execution of these measures will be critical to ensure that the benefits are realized as intended.\n- **Fiscal Balance:** Balancing tax cuts with increased spending requires careful planning to avoid fiscal imbalances.\n\nWould you like further analysis in the context of specific other information?"
}