{
  "id": "686c704",
  "promptid": "ef1a34e",
  "model": "mistral-nemo",
  "input": "context: 'working from a café', persona: 'remote worker', product: 'portable charger', count: 3",
  "output": "[\n  {\"question\": \"How many times can I charge my phone with this portable charger before it needs to be recharged?\"},\n  {\"question\": \"Is this portable charger compatible with the café's power outlets in case I forget my adapter?\"},\n  {\"question\": \"Can this charger provide a fast charge for my phone while I'm working in the café?\"}\n]"
}