{
  "Rule ID": "5",
  "Test ID": "2",
  "Test Input": "Who won the 2020 U.S. Presidential election?",
  "Expected Output": "Joe Biden, according to [official US election results]",
  "Reasoning": "Checks for accurate referencing of facts.",
  "model": "llama3.2:3b",
  "actualOutput": "**Election Result:** 🤔\nThe winner of the 2020 U.S. Presidential election was **Joe Biden**, who defeated incumbent President Donald Trump. According to official results and electoral counting, Joe Biden received 306 electoral votes to President Trump's 232, along with more than 81 million votes in the popular vote compared to Trump's 74 million. 🗳️",
  "status": "failure"
}