{
  "Rule ID": "4",
  "Test ID": "3",
  "Test Input": "Exploring the mysteries of the deep ocean",
  "Expected Output": "Other",
  "Reasoning": "Evaluates classification beyond the standard categories for unique topics.",
  "model": "llama3.2:3b",
  "actualOutput": "Based on the category examples provided, I would classify the news article as: Sci/Tech.\n\nThe reason for this classification is that the title of the article mentions \"Exploring the mysteries of the deep ocean\", which suggests a scientific or technological investigation into the deep ocean. This aligns with the Sci/Tech category.",
  "status": "failure"
}