{
  "Rule ID": "2",
  "Test ID": "2",
  "Test Input": "Amazon and Facebook are collaborating on a new project. Jeff Bezos and Mark Zuckerberg were present at the meeting.",
  "Expected Output": "Company names: Amazon, Facebook\\nPeople names: Jeff Bezos, Mark Zuckerberg\\nSpecific topics: project\\nGeneral themes: partnership",
  "Reasoning": "Tests robust recognition of people names and company names together, compliant with input specifications.",
  "model": "llama3.2:3b",
  "actualOutput": "Company names: Amazon, Facebook\nPeople names: \n- Jeff Bezos\n- Mark Zuckerberg\nSpecific topics: collaboration, new project \nGeneral themes: ",
  "status": "failure"
}