{
  "Rule ID": "5",
  "Test ID": "1",
  "Test Input": "The global economy is shifting due to technological advancements. Would you like further analysis in the context of these changes?",
  "Expected Output": "Prompt asking if further analysis is needed, followed by a structured response if required.",
  "Reasoning": "Tests the software's ability to inquire about further analysis and provide structured responses.",
  "model": "llama3.2:3b",
  "actualOutput": "## Overview\n\nThere is no overview section as this conversation has just begun.\n\n## Summary\n\nThe global economy is shifting due to technological advancements, which may lead to significant changes in various sectors, including manufacturing, services, and employment. The increasing use of automation, artificial intelligence, and the internet of things (IoT) is transforming the way businesses operate, creating new opportunities for growth and innovation.\n\n## Deep Dive Analysis\n\n### **Related Industries**\n\nThe shift in the global economy due to technological advancements is expected to have a profound impact on various industries:\n\n*   **Manufacturing**: Automation and robotics are increasing productivity and reducing labor costs, but also pose a significant threat to jobs.\n*   **Services**: The digital transformation of services such as finance, healthcare, and education is creating new business opportunities, but also requires significant investments in technology and talent.\n*   **E-commerce**: The rise of e-commerce platforms and online marketplaces is changing the way consumers shop and businesses operate.\n\n### **Political Economy**\n\nThe shift in the global economy due to technological advancements has significant implications for international trade and politics:\n\n*   **Globalization**: Technological advancements are reducing barriers to trade, but also creating new challenges for regulation and oversight.\n*   **Protectionism**: Some governments are responding to job losses and economic disruption by implementing protectionist policies, which could harm global trade.\n*   **Innovation Policy**: Governments are investing in innovation and R\\&D to support the development of new technologies and industries.\n\n### **Social Implications**\n\nThe shift in the global economy due to technological advancements also has significant social implications:\n\n*   **Job Displacement**: Automation and AI may displace certain jobs, particularly those that involve repetitive tasks.\n*   **Skills Development**: The increasing use of technology requires workers to develop new skills, such as data analysis and digital literacy.\n*   **Inequality**: The benefits of technological advancements are not being evenly distributed, with some individuals and groups facing significant economic disruption.\n\n### **Potential Implications**\n\nThe shift in the global economy due to technological advancements has significant potential implications for:\n\n*   **GDP Growth**: Technological advancements can lead to increased productivity and GDP growth.\n*   **Innovation**: The development of new technologies and industries can drive innovation and entrepreneurship.\n*   **Global Stability**: The increasing use of technology requires a coordinated approach to regulation, oversight, and security.\n\n## Next Steps\n\nWould you like me to expand on any of these topics or provide further analysis in the context of specific other information?",
  "status": "failure"
}